{
  "nav": 12426.25,
  "cash": 1199.57,
  "peak": 12426.25,
  "dd_pct": 0.0,
  "circuit_breaker": false,
  "inception": "2026-04-27T14:05:00+00:00",
  "last_updated": "2026-05-02T18:32:45.940738+00:00",
  "notes": "Saturday tick \u2014 US equities closed (weekend). Fresh crypto: BTC +0.17%, ETH +0.62%, SOL +0.48%. NAV flat. All positions within caps. No entries/exits warranted.",
  "stats": {
    "closed": 15,
    "wins": 4,
    "losses": 10,
    "scratches": 0,
    "win_rate": 28.57,
    "realized_pnl": 2309.49,
    "best_ticker": "SPY260504C724",
    "best_pnl": 50.33,
    "worst_ticker": "SPY260504P711",
    "worst_pnl": -2702.9
  },
  "reconcile": {
    "status": "ok"
  }
}